odoo/addons/__init__.py
odoo/addons/lunch/__init__.py
odoo/addons/lunch/__manifest__.py
odoo/addons/lunch/data/lunch_data.xml
odoo/addons/lunch/data/lunch_demo.xml
odoo/addons/lunch/i18n/af.po
odoo/addons/lunch/i18n/am.po
odoo/addons/lunch/i18n/ar.po
odoo/addons/lunch/i18n/bg.po
odoo/addons/lunch/i18n/bs.po
odoo/addons/lunch/i18n/ca.po
odoo/addons/lunch/i18n/cs.po
odoo/addons/lunch/i18n/da.po
odoo/addons/lunch/i18n/de.po
odoo/addons/lunch/i18n/el.po
odoo/addons/lunch/i18n/en_AU.po
odoo/addons/lunch/i18n/en_GB.po
odoo/addons/lunch/i18n/es.po
odoo/addons/lunch/i18n/es_BO.po
odoo/addons/lunch/i18n/es_CL.po
odoo/addons/lunch/i18n/es_CO.po
odoo/addons/lunch/i18n/es_CR.po
odoo/addons/lunch/i18n/es_DO.po
odoo/addons/lunch/i18n/es_EC.po
odoo/addons/lunch/i18n/es_PE.po
odoo/addons/lunch/i18n/es_PY.po
odoo/addons/lunch/i18n/es_VE.po
odoo/addons/lunch/i18n/et.po
odoo/addons/lunch/i18n/eu.po
odoo/addons/lunch/i18n/fa.po
odoo/addons/lunch/i18n/fi.po
odoo/addons/lunch/i18n/fo.po
odoo/addons/lunch/i18n/fr.po
odoo/addons/lunch/i18n/fr_BE.po
odoo/addons/lunch/i18n/fr_CA.po
odoo/addons/lunch/i18n/gl.po
odoo/addons/lunch/i18n/gu.po
odoo/addons/lunch/i18n/he.po
odoo/addons/lunch/i18n/hi.po
odoo/addons/lunch/i18n/hr.po
odoo/addons/lunch/i18n/hu.po
odoo/addons/lunch/i18n/id.po
odoo/addons/lunch/i18n/is.po
odoo/addons/lunch/i18n/it.po
odoo/addons/lunch/i18n/ja.po
odoo/addons/lunch/i18n/ka.po
odoo/addons/lunch/i18n/kab.po
odoo/addons/lunch/i18n/ko.po
odoo/addons/lunch/i18n/lo.po
odoo/addons/lunch/i18n/lt.po
odoo/addons/lunch/i18n/lv.po
odoo/addons/lunch/i18n/mk.po
odoo/addons/lunch/i18n/mn.po
odoo/addons/lunch/i18n/nb.po
odoo/addons/lunch/i18n/ne.po
odoo/addons/lunch/i18n/nl.po
odoo/addons/lunch/i18n/nl_BE.po
odoo/addons/lunch/i18n/pl.po
odoo/addons/lunch/i18n/pt.po
odoo/addons/lunch/i18n/pt_BR.po
odoo/addons/lunch/i18n/ro.po
odoo/addons/lunch/i18n/ru.po
odoo/addons/lunch/i18n/sk.po
odoo/addons/lunch/i18n/sl.po
odoo/addons/lunch/i18n/sq.po
odoo/addons/lunch/i18n/sr.po
odooku_odoo_lunch-11.0.7.dist-info/LICENSE
odooku_odoo_lunch-11.0.7.dist-info/METADATA
odooku_odoo_lunch-11.0.7.dist-info/WHEEL
odooku_odoo_lunch-11.0.7.dist-info/top_level.txt
odooku_odoo_lunch-11.0.7.dist-info/RECORD
